chardet-stubs/METADATA.toml
chardet-stubs/__init__.pyi
chardet-stubs/enums.pyi
chardet-stubs/langbulgarianmodel.pyi
chardet-stubs/langcyrillicmodel.pyi
chardet-stubs/langgreekmodel.pyi
chardet-stubs/langhebrewmodel.pyi
chardet-stubs/langhungarianmodel.pyi
chardet-stubs/langthaimodel.pyi
chardet-stubs/langturkishmodel.pyi
chardet-stubs/universaldetector.pyi
chardet-stubs/version.pyi
types_chardet-5.0.4.5.dist-info/METADATA
types_chardet-5.0.4.5.dist-info/WHEEL
types_chardet-5.0.4.5.dist-info/top_level.txt
types_chardet-5.0.4.5.dist-info/RECORD
